flex_plot/__init__.py
flex_plot/cli/__init__.py
flex_plot/cli/run.py
flex_plot/flex_plot_config.py
flex_plot/flex_plot_runner.py
flex_plot/script_context.py
flex_plot-0.1.0.dist-info/entry_points.txt
flex_plot-0.1.0.dist-info/WHEEL
flex_plot-0.1.0.dist-info/METADATA
flex_plot-0.1.0.dist-info/RECORD
