Metadata-Version: 2.1
Name: flex-plot
Version: 0.1.0
Summary: 
Author: Ilyas Kuhlemann
Author-email: ilyasp.ku@gmail.com
Requires-Python: >=3.8,<4.0
Classifier: Programming Language :: Python :: 3
Classifier: Programming Language :: Python :: 3.8
Classifier: Programming Language :: Python :: 3.9
Requires-Dist: matplotlib (>=3.1,<4.0)
Requires-Dist: toml (>=0.10.2,<0.11.0)
